supy/__init__.py
supy/computervision.py
supy/database.py
supy/database_inputmask.py
supy/database_inputmask3.py
supy/forms.py
supy/forms3.py
supy/guimaker.py
supy/guimaker3.py
supy/multibase.py
supy/rgps.py
supy/serialize.py
supy/signals.py
supy/sqldatabase.py
supy/sqldatabase_inputmask.py
supy/sqlforms.py
supy/sqltableeditor.py
supy/utilities.py
supy/widgets.py
supylib-0.52.dist-info/LICENSE
supylib-0.52.dist-info/METADATA
supylib-0.52.dist-info/WHEEL
supylib-0.52.dist-info/top_level.txt
supylib-0.52.dist-info/RECORD
