Metadata-Version: 2.1
Name: supylib
Version: 0.52
Summary: A Python-based utility library for databases, computer vision, signal processing, and machine learning
Home-page: https://github.com/aknoblauch/supylib
Author: Andreas Knoblauch
Author-email: knoblauch@hs-albsig.de
License: UNKNOWN
Project-URL: Bug Tracker, https://github.com/aknoblauch/supylib/issues
Platform: UNKNOWN
Classifier: Programming Language :: Python :: 3
Classifier: License :: OSI Approved :: MIT License
Classifier: Operating System :: OS Independent
Requires-Python: >=3.6
License-File: LICENSE
